{
  "version": "5",
  "dialect": "pg",
  "entries": [
    {
      "idx": 0,
      "version": "5",
      "when": 1713532244111,
      "tag": "0000_chemical_blazing_skull",
      "breakpoints": true
    },
    {
      "idx": 1,
      "version": "5",
      "when": 1713985077864,
      "tag": "0001_tiresome_maximus",
      "breakpoints": true
    },
    {
      "idx": 2,
      "version": "5",
      "when": 1715539560166,
      "tag": "0002_fearless_romulus",
      "breakpoints": true
    },
    {
      "idx": 3,
      "version": "5",
      "when": 1722555370603,
      "tag": "0003_nice_newton_destine",
      "breakpoints": true
    },
    {
      "idx": 4,
      "version": "5",
      "when": 1722555417793,
      "tag": "0004_nosy_james_howlett",
      "breakpoints": true
    },
    {
      "idx": 5,
      "version": "5",
      "when": 1722555439636,
      "tag": "0005_steep_havok",
      "breakpoints": true
    },
    {
      "idx": 6,
      "version": "5",
      "when": 1726448929896,
      "tag": "0006_flimsy_colossus",
      "breakpoints": true
    }
  ]
}